{
  "expenseItems": [
    {
      "id": "727212a0-4d73-4615-bd23-d7df6f562491",
      "purchasedOn": "2001-02-18",
      "nature": "Restaurant",
      "originalAmount": {
        "amount": 46.5,
        "currency": "GBP"
      },
      "convertedAmount": {
        "amount": 55.34,
        "currency": "EUR"
      },
      "comment": "Mission de 5 jours à Londres",
      "createdAt": "2018-12-05T14:00:34.435154Z",
      "lastModifiedAt": "2022-04-26T15:23:43.389Z"
    },
    {
      "id": "727212a5-4d73-4615-bd23-d7df6f562491",
      "purchasedOn": "2018-02-08",
      "nature": "Spa",
      "originalAmount": {
        "amount": 18,
        "currency": "GBP"
      },
      "convertedAmount": {
        "amount": 21.42,
        "currency": "EUR"
      },
      "comment": "Mission de 5 jours à Londres",
      "createdAt": "2018-12-05T14:00:34.435154Z",
      "lastModifiedAt": "2022-04-26T16:15:43.983Z"
    },
    {
      "nature": "Taxi",
      "purchasedOn": "2022-04-28",
      "originalAmount": {
        "amount": 25,
        "currency": "EUR"
      },
      "convertedAmount": {
        "amount": 25,
        "currency": "EUR"
      },
      "createdAt": "2022-04-25T22:51:21.634Z",
      "lastModifiedAt": "2022-04-25T22:51:21.634Z",
      "id": "cb3ea5db-b29a-4ef3-91ec-2586e67731dc"
    },
    {
      "nature": "Courses",
      "purchasedOn": "2021-01-05",
      "originalAmount": {
        "amount": 80,
        "currency": "USD"
      },
      "convertedAmount": {
        "amount": 74.4,
        "currency": "EUR"
      },
      "createdAt": "2022-04-25T22:53:22.859Z",
      "lastModifiedAt": "2022-04-25T22:53:22.859Z",
      "id": "bf1e438b-8b55-4a5f-a8ff-4490af0f7e4d"
    },
    {
      "nature": "Avion",
      "purchasedOn": "2022-04-26",
      "originalAmount": {
        "amount": 480,
        "currency": "EUR"
      },
      "convertedAmount": {
        "amount": 480,
        "currency": "EUR"
      },
      "comment": "Voyage d'affaires en Europe",
      "createdAt": "2022-04-25T23:03:38.977Z",
      "lastModifiedAt": "2022-04-25T23:03:46.298Z",
      "id": "434230ea-9687-465c-83f0-9e453593cc21"
    },
    {
      "nature": "Ubereat",
      "purchasedOn": "2022-04-12",
      "originalAmount": {
        "amount": 28,
        "currency": "GBP"
      },
      "convertedAmount": {
        "amount": 33.32,
        "currency": "EUR"
      },
      "comment": "",
      "createdAt": "2022-04-25T23:04:14.327Z",
      "lastModifiedAt": "2022-04-25T23:08:16.002Z",
      "id": "16013d48-8b83-4d4f-972d-65770d5aed8c"
    },
    {
      "nature": "Restaurant",
      "purchasedOn": "2020-11-02",
      "originalAmount": {
        "amount": 45,
        "currency": "USD"
      },
      "convertedAmount": {
        "amount": 41.85,
        "currency": "EUR"
      },
      "comment": "",
      "createdAt": "2022-04-25T23:04:57.479Z",
      "lastModifiedAt": "2022-04-25T23:04:57.479Z",
      "id": "b47cb88b-5ceb-40c2-99d9-429464c8d831"
    },
    {
      "nature": "Hotel",
      "purchasedOn": "2012-02-28",
      "originalAmount": {
        "amount": 80,
        "currency": "EUR"
      },
      "convertedAmount": {
        "amount": 80,
        "currency": "EUR"
      },
      "comment": "",
      "createdAt": "2022-04-25T23:05:24.342Z",
      "lastModifiedAt": "2022-04-25T23:05:24.342Z",
      "id": "36c387b8-a656-45cf-b2ed-afb481d20f7e"
    },
    {
      "nature": "Spa",
      "purchasedOn": "2018-12-28",
      "originalAmount": {
        "amount": 65,
        "currency": "USD"
      },
      "convertedAmount": {
        "amount": 60.45,
        "currency": "EUR"
      },
      "comment": "",
      "createdAt": "2022-04-25T23:06:35.757Z",
      "lastModifiedAt": "2022-04-25T23:07:27.957Z",
      "id": "8f55aed9-06fd-4dbf-9bfd-ea63ec169dd5"
    },
    {
      "nature": "Tabac",
      "purchasedOn": "2015-08-22",
      "originalAmount": {
        "amount": 12,
        "currency": "EUR"
      },
      "convertedAmount": {
        "amount": 12,
        "currency": "EUR"
      },
      "comment": "Tabac",
      "createdAt": "2022-04-26T14:56:45.373Z",
      "lastModifiedAt": "2022-04-26T14:56:45.373Z",
      "id": "abbb4ed1-90de-457e-9871-1ed439e682d3"
    },
    {
      "nature": "Ubereats",
      "purchasedOn": "2020-04-18",
      "originalAmount": {
        "amount": 45,
        "currency": "GBP"
      },
      "convertedAmount": {
        "amount": 54,
        "currency": "EUR"
      },
      "createdAt": "2022-04-26T15:01:51.914Z",
      "lastModifiedAt": "2022-04-26T15:01:51.914Z",
      "id": "156b71ca-e656-47e8-ba43-7aef8d655cdc"
    },
    {
      "nature": "Baguette de pain",
      "purchasedOn": "2019-08-12",
      "originalAmount": {
        "amount": 1,
        "currency": "EUR"
      },
      "convertedAmount": {
        "amount": 1,
        "currency": "EUR"
      },
      "comment": "",
      "createdAt": "2022-04-26T15:11:12.513Z",
      "lastModifiedAt": "2022-04-26T15:11:12.513Z",
      "id": "d5fa100d-4b26-478f-af09-3b86d472fd49"
    }
  ]
}